{
  "": "",
  "Ajhvf ": "",
  "Lorem ipsum dolor sit amet, consectetur adipiscing elit, sed do eiusmod tempor incididunt ut labore et dolore magna aliqua": "",
  "Not found": "",
  "Profile page": "",
  "Toggle": "",
  "decrement": "",
  "increment": "",
  "Айти": "",
  "В": "",
  "Вs": "",
  "Вsq": "",
  "Ваша фамилия": "",
  "Ваше имя": "",
  "Введите имя": "",
  "Введите пароль": "",
  "Введите текст комментария": "",
  "Войти": "",
  "Все статьи": "",
  "Вы": "",
  "Вы ввели неверный логин и пароль": "",
  "Вы ввели неверный логин или пароль": "",
  "Выйти": "",
  "Выйь": "",
  "Выкинуть ошибку": "",
  "Главная": "",
  "Данные не указаны": "",
  "Имя": "",
  "Имя, фамилия, логин обя": "",
  "Имя, фамилия, логин обязательны": "",
  "Имяб ": "",
  "Комментраии отсутствуют": "",
  "Н": "",
  "Наука": "",
  "Не указана валюта": "",
  "Не указана страна": "",
  "Некорректный ": "",
  "Некорректный возраст": "",
  "Нк": "",
  "О сайте": "",
  "Обновить страницу": "",
  "Отменить": "",
  "Отправить": "",
  "Поиск": "",
  "Произошла непредвиденная ошибка": "",
  "Произошла ошибка при загрузке статьи": "",
  "Профиль": "",
  "Редактировать": "",
  "Серверная ошибка при сохранении": "",
  "Сортировать ПО": "",
  "Сохранить": "",
  "Ст": "",
  "Статьи не найдены": "",
  "Укажите вашу ": "",
  "Укажите вашу валюту": "",
  "Укажите вашу страну": "",
  "Форма авторизауц": "",
  "Форма авторизации": "",
  "Читать далее ": {
    "": {
      "": {
        "": ""
      }
    }
  },
  "Экономика": "",
  "Язык": "",
  "возрастанию": "",
  "дате создания": "",
  "названию": "",
  "по": "",
  "просмотрам": "",
  "убыванию": ""
}
